decrypt/__init__.py
decrypt/__version__.py
decrypt/decrypt.py
encrypt/__init__.py
encrypt/__version__.py
encrypt/encrypt.py
chineseencryptordecrypt-0.2.0.dist-info/LICENSE
chineseencryptordecrypt-0.2.0.dist-info/METADATA
chineseencryptordecrypt-0.2.0.dist-info/WHEEL
chineseencryptordecrypt-0.2.0.dist-info/top_level.txt
chineseencryptordecrypt-0.2.0.dist-info/RECORD
