Metadata-Version: 2.1
Name: chineseencryptordecrypt
Version: 0.2.0
Summary: My make a encrypt and decrypt module.It from China.It small.
Home-page: https://github.com/me/myproject
Author: 15989116376
Author-email: lsd.bb770810.com@outlook.com
License: MIT
Classifier: License :: OSI Approved :: MIT License
Classifier: Programming Language :: Python
Classifier: Programming Language :: Python :: 3
Classifier: Programming Language :: Python :: 3.6
Classifier: Programming Language :: Python :: Implementation :: CPython
Classifier: Programming Language :: Python :: Implementation :: PyPy
Requires-Python: >=3.6.0
License-File: LICENSE
